fconv/__init__.py
fconv/__main__.py
fconv/core.py
fconv/util.py
fconv/formats/__init__.py
fconv/formats/base.py
fconv/formats/json.py
fconv/formats/toml.py
fconv/formats/xml.py
fconv/formats/yaml.py
fconv-3.2.2.dist-info/LICENSE
fconv-3.2.2.dist-info/METADATA
fconv-3.2.2.dist-info/WHEEL
fconv-3.2.2.dist-info/entry_points.txt
fconv-3.2.2.dist-info/top_level.txt
fconv-3.2.2.dist-info/RECORD
