Metadata-Version: 2.1
Name: fconv
Version: 3.2.2
Summary: Converter between multiple open-standard file formats.
Home-page: https://github.com/wf001/fconv
Author: wf001
Author-email: wf001@diax.xyz
License: MIT
Classifier: Programming Language :: Python :: 3.8
Classifier: Programming Language :: Python :: 3.9
Classifier: Programming Language :: Python :: 3.10
Classifier: Programming Language :: Python :: 3.11
Classifier: Topic :: Software Development :: Libraries :: Python Modules
Classifier: Topic :: Text Processing
License-File: LICENSE
Requires-Dist: PyYAML (==6.0)
Requires-Dist: toml (==0.10.2)
Requires-Dist: xmltodict (==0.13.0)
